AUTHORS
MANIFEST.in
README.rst
requirements.txt
setup.py
rosixdocs/__init__.py
rosixdocs/__init__.pyc
rosixdocs/testmodule.py
rosixdocs/testmodule.pyc
rosixdocs.egg-info/PKG-INFO
rosixdocs.egg-info/SOURCES.txt
rosixdocs.egg-info/dependency_links.txt
rosixdocs.egg-info/not-zip-safe
rosixdocs.egg-info/requires.txt
rosixdocs.egg-info/top_level.txt
rosixdocs/themes/html/domainindex.html
rosixdocs/themes/html/genindex.html
rosixdocs/themes/html/layout.html
rosixdocs/themes/html/navbar.html
rosixdocs/themes/html/search.html
rosixdocs/themes/html/searchbox.html
rosixdocs/themes/html/sourcelink.html
rosixdocs/themes/html/theme.conf
rosixdocs/themes/html/static/frame.css
rosixdocs/themes/html/static/listitem.png
rosixdocs/themes/html/static/main.css
rosixdocs/themes/html/static/scroll.js
rosixdocs/themes/html/static/style.css
rosixdocs/themes/html/static/bootstrap/LICENSE
rosixdocs/themes/html/static/bootstrap/config.json
rosixdocs/themes/html/static/bootstrap/css/bootstrap-theme.css
rosixdocs/themes/html/static/bootstrap/css/bootstrap-theme.min.css
rosixdocs/themes/html/static/bootstrap/css/bootstrap.css
rosixdocs/themes/html/static/bootstrap/css/bootstrap.min.css
rosixdocs/themes/html/static/bootstrap/js/bootstrap.js
rosixdocs/themes/html/static/bootstrap/js/bootstrap.min.js
rosixdocs/themes/html/static/font-awesome/css/LICENSE
rosixdocs/themes/html/static/font-awesome/css/font-awesome.css
rosixdocs/themes/html/static/font-awesome/css/font-awesome.min.css
rosixdocs/themes/html/static/font-awesome/fonts/FontAwesome.otf
rosixdocs/themes/html/static/font-awesome/fonts/LICENSE
rosixdocs/themes/html/static/font-awesome/fonts/fontawesome-webfont.eot
rosixdocs/themes/html/static/font-awesome/fonts/fontawesome-webfont.svg
rosixdocs/themes/html/static/font-awesome/fonts/fontawesome-webfont.ttf
rosixdocs/themes/html/static/font-awesome/fonts/fontawesome-webfont.woff
rosixdocs/themes/html/static/font-awesome/fonts/fontawesome-webfont.woff2